MANIFEST.in
README.md
setup.py
mtgtransform/__init__.py
mtgtransform/main.py
mtgtransform.egg-info/PKG-INFO
mtgtransform.egg-info/SOURCES.txt
mtgtransform.egg-info/dependency_links.txt
mtgtransform.egg-info/entry_points.txt
mtgtransform.egg-info/top_level.txt