Metadata-Version: 1.0
Name: mtgtransform
Version: 0.0.5
Summary: Magic the Gathering deck transformator.
Home-page: https://github.com/leinz/mtgtransform
Author: Børge Lanes
Author-email: borge.lanes@gmail.com
License: MIT
Keywords: mtg
Platform: UNKNOWN
